{
  "folders": [
    {
      "id": "GR3JmDRrRjVzzeys",
      "name": "kjasklalskajsas updated",
      "parentFolderId": null,
      "homeProjectId": "mvlNse9tTm3JeDvz",
      "createdAt": "Thu, 20 Mar 2025 02:27:18 GMT",
      "updatedAt": "Thu, 20 Mar 2025 03:13:30 GMT"
    },
    {
      "id": "P8eyYcK430JwA5mx",
      "name": "yet another folder",
      "parentFolderId": null,
      "homeProjectId": "mvlNse9tTm3JeDvz",
      "createdAt": "Thu, 20 Mar 2025 03:03:28 GMT",
      "updatedAt": "Thu, 20 Mar 2025 03:03:28 GMT"
    },
    {
      "id": "ngHPeaXGVIoN10d8",
      "name": "yet yet another folder",
      "parentFolderId": null,
      "homeProjectId": "mvlNse9tTm3JeDvz",
      "createdAt": "Thu, 20 Mar 2025 03:04:17 GMT",
      "updatedAt": "Thu, 20 Mar 2025 03:04:17 GMT"
    },
    {
      "id": "MNkUz9n2QClPSQk4",
      "name": "perro",
      "parentFolderId": null,
      "homeProjectId": "mvlNse9tTm3JeDvz",
      "createdAt": "Thu, 20 Mar 2025 03:06:01 GMT",
      "updatedAt": "Thu, 20 Mar 2025 03:06:01 GMT"
    },
    {
      "id": "cvXWtchLk8S34sqe",
      "name": "folder papa",
      "parentFolderId": null,
      "homeProjectId": "mvlNse9tTm3JeDvz",
      "createdAt": "Thu, 20 Mar 2025 03:06:57 GMT",
      "updatedAt": "Thu, 20 Mar 2025 03:06:57 GMT"
    },
    {
      "id": "6XeDWMZrDbqA8GP9",
      "name": "opa",
      "parentFolderId": null,
      "homeProjectId": "mvlNse9tTm3JeDvz",
      "createdAt": "Thu, 20 Mar 2025 03:10:47 GMT",
      "updatedAt": "Thu, 20 Mar 2025 03:10:47 GMT"
    },
    {
      "id": "JOzOxfVIt9zpqKDf",
      "name": "que bolas",
      "parentFolderId": null,
      "homeProjectId": "mvlNse9tTm3JeDvz",
      "createdAt": "Thu, 20 Mar 2025 03:18:14 GMT",
      "updatedAt": "Thu, 20 Mar 2025 03:18:14 GMT"
    }
  ]
}